{
  "episode_index": 7,
  "task": "Pour the black powder into the mortar and grind.",
  "n_frames": 1141,
  "fps": 30,
  "annotator": "auto-signal",
  "method": "signal-derived (tube grip dim3 + pestle grip dim13 + carrier-drift pour/grind)",
  "critical_points": [
    155,
    222,
    364,
    666,
    735,
    1016
  ],
  "critical_names": [
    "grasp_tube",
    "start_pour",
    "release_tube",
    "grasp_pestle",
    "start_grind",
    "lift_pestle"
  ],
  "subtask_starts": [
    0,
    155,
    222,
    364,
    666,
    735,
    1016
  ],
  "flags": [],
  "n_subtasks": 7,
  "subtasks": [
    {
      "subtask_id": 0,
      "label": "reach for the test tube",
      "start_frame": 0,
      "end_frame": 154,
      "start_t": 0.0,
      "end_t": 5.13,
      "n_frames": 155,
      "dur_s": 5.17
    },
    {
      "subtask_id": 1,
      "label": "lift the test tube and move it over the mortar",
      "start_frame": 155,
      "end_frame": 221,
      "start_t": 5.17,
      "end_t": 7.37,
      "n_frames": 67,
      "dur_s": 2.23
    },
    {
      "subtask_id": 2,
      "label": "pour the black powder into the mortar",
      "start_frame": 222,
      "end_frame": 363,
      "start_t": 7.4,
      "end_t": 12.1,
      "n_frames": 142,
      "dur_s": 4.73
    },
    {
      "subtask_id": 3,
      "label": "release the test tube and reach for the pestle",
      "start_frame": 364,
      "end_frame": 665,
      "start_t": 12.13,
      "end_t": 22.17,
      "n_frames": 302,
      "dur_s": 10.07
    },
    {
      "subtask_id": 4,
      "label": "bring the pestle over the mortar",
      "start_frame": 666,
      "end_frame": 734,
      "start_t": 22.2,
      "end_t": 24.47,
      "n_frames": 69,
      "dur_s": 2.3
    },
    {
      "subtask_id": 5,
      "label": "grind the powder in the mortar",
      "start_frame": 735,
      "end_frame": 1015,
      "start_t": 24.5,
      "end_t": 33.83,
      "n_frames": 281,
      "dur_s": 9.37
    },
    {
      "subtask_id": 6,
      "label": "lift the pestle and return to rest",
      "start_frame": 1016,
      "end_frame": 1140,
      "start_t": 33.87,
      "end_t": 38.0,
      "n_frames": 125,
      "dur_s": 4.17
    }
  ]
}