{
  "episode_index": 15,
  "task": "Pour the black powder into the mortar and grind.",
  "n_frames": 1227,
  "fps": 30,
  "annotator": "auto-signal",
  "method": "signal-derived (tube grip dim3 + pestle grip dim13 + carrier-drift pour/grind)",
  "critical_points": [
    174,
    252,
    421,
    726,
    769,
    1110
  ],
  "critical_names": [
    "grasp_tube",
    "start_pour",
    "release_tube",
    "grasp_pestle",
    "start_grind",
    "lift_pestle"
  ],
  "subtask_starts": [
    0,
    174,
    252,
    421,
    726,
    769,
    1110
  ],
  "flags": [],
  "n_subtasks": 7,
  "subtasks": [
    {
      "subtask_id": 0,
      "label": "reach for the test tube",
      "start_frame": 0,
      "end_frame": 173,
      "start_t": 0.0,
      "end_t": 5.77,
      "n_frames": 174,
      "dur_s": 5.8
    },
    {
      "subtask_id": 1,
      "label": "lift the test tube and move it over the mortar",
      "start_frame": 174,
      "end_frame": 251,
      "start_t": 5.8,
      "end_t": 8.37,
      "n_frames": 78,
      "dur_s": 2.6
    },
    {
      "subtask_id": 2,
      "label": "pour the black powder into the mortar",
      "start_frame": 252,
      "end_frame": 420,
      "start_t": 8.4,
      "end_t": 14.0,
      "n_frames": 169,
      "dur_s": 5.63
    },
    {
      "subtask_id": 3,
      "label": "release the test tube and reach for the pestle",
      "start_frame": 421,
      "end_frame": 725,
      "start_t": 14.03,
      "end_t": 24.17,
      "n_frames": 305,
      "dur_s": 10.17
    },
    {
      "subtask_id": 4,
      "label": "bring the pestle over the mortar",
      "start_frame": 726,
      "end_frame": 768,
      "start_t": 24.2,
      "end_t": 25.6,
      "n_frames": 43,
      "dur_s": 1.43
    },
    {
      "subtask_id": 5,
      "label": "grind the powder in the mortar",
      "start_frame": 769,
      "end_frame": 1109,
      "start_t": 25.63,
      "end_t": 36.97,
      "n_frames": 341,
      "dur_s": 11.37
    },
    {
      "subtask_id": 6,
      "label": "lift the pestle and return to rest",
      "start_frame": 1110,
      "end_frame": 1226,
      "start_t": 37.0,
      "end_t": 40.87,
      "n_frames": 117,
      "dur_s": 3.9
    }
  ]
}