{
  "episode_index": 27,
  "task": "Pour the black powder into the mortar and grind.",
  "n_frames": 1161,
  "fps": 30,
  "method": "signal-derived (state-dim3 pour deviation + carrier-drift grind)",
  "boundaries": {
    "b1": 196,
    "b2": 396,
    "b3": 762,
    "b4": 1020
  },
  "flags": [],
  "n_subtasks": 5,
  "subtasks": [
    {
      "subtask_id": 0,
      "label": "reach for and grasp the powder container",
      "start_frame": 0,
      "end_frame": 195,
      "start_t": 0.0,
      "end_t": 6.5,
      "n_frames": 196,
      "dur_s": 6.53
    },
    {
      "subtask_id": 1,
      "label": "pour the black powder into the mortar",
      "start_frame": 196,
      "end_frame": 396,
      "start_t": 6.53,
      "end_t": 13.2,
      "n_frames": 201,
      "dur_s": 6.7
    },
    {
      "subtask_id": 2,
      "label": "set down the container and bring the pestle to the mortar",
      "start_frame": 397,
      "end_frame": 761,
      "start_t": 13.23,
      "end_t": 25.37,
      "n_frames": 365,
      "dur_s": 12.17
    },
    {
      "subtask_id": 3,
      "label": "grind the powder in the mortar",
      "start_frame": 762,
      "end_frame": 1020,
      "start_t": 25.4,
      "end_t": 34.0,
      "n_frames": 259,
      "dur_s": 8.63
    },
    {
      "subtask_id": 4,
      "label": "lift the pestle and return to rest",
      "start_frame": 1021,
      "end_frame": 1160,
      "start_t": 34.03,
      "end_t": 38.67,
      "n_frames": 140,
      "dur_s": 4.67
    }
  ]
}