{
  "episode_index": 21,
  "task": "Pour the black powder into the mortar and grind.",
  "n_frames": 1084,
  "fps": 30,
  "annotator": "auto-signal",
  "method": "signal-derived (state-dim3 tube-held window + carrier-drift pour/grind)",
  "critical_points": [
    177,
    233,
    350,
    709,
    970
  ],
  "subtask_starts": [
    0,
    177,
    233,
    350,
    709,
    970
  ],
  "flags": [],
  "n_subtasks": 6,
  "subtasks": [
    {
      "subtask_id": 0,
      "label": "reach for the test tube",
      "start_frame": 0,
      "end_frame": 176,
      "start_t": 0.0,
      "end_t": 5.87,
      "n_frames": 177,
      "dur_s": 5.9
    },
    {
      "subtask_id": 1,
      "label": "lift the test tube and move it over the mortar",
      "start_frame": 177,
      "end_frame": 232,
      "start_t": 5.9,
      "end_t": 7.73,
      "n_frames": 56,
      "dur_s": 1.87
    },
    {
      "subtask_id": 2,
      "label": "pour the black powder into the mortar",
      "start_frame": 233,
      "end_frame": 349,
      "start_t": 7.77,
      "end_t": 11.63,
      "n_frames": 117,
      "dur_s": 3.9
    },
    {
      "subtask_id": 3,
      "label": "set down the test tube and pick up the pestle",
      "start_frame": 350,
      "end_frame": 708,
      "start_t": 11.67,
      "end_t": 23.6,
      "n_frames": 359,
      "dur_s": 11.97
    },
    {
      "subtask_id": 4,
      "label": "grind the powder in the mortar",
      "start_frame": 709,
      "end_frame": 969,
      "start_t": 23.63,
      "end_t": 32.3,
      "n_frames": 261,
      "dur_s": 8.7
    },
    {
      "subtask_id": 5,
      "label": "lift the pestle and return to rest",
      "start_frame": 970,
      "end_frame": 1083,
      "start_t": 32.33,
      "end_t": 36.1,
      "n_frames": 114,
      "dur_s": 3.8
    }
  ]
}