{
  "episode_index": 35,
  "task": "Pour the black powder into the mortar and grind.",
  "n_frames": 1157,
  "fps": 30,
  "annotator": "auto-signal",
  "method": "signal-derived (state-dim3 tube-held window + carrier-drift pour/grind)",
  "critical_points": [
    190,
    275,
    412,
    734,
    1018
  ],
  "subtask_starts": [
    0,
    190,
    275,
    412,
    734,
    1018
  ],
  "flags": [],
  "n_subtasks": 6,
  "subtasks": [
    {
      "subtask_id": 0,
      "label": "reach for the test tube",
      "start_frame": 0,
      "end_frame": 189,
      "start_t": 0.0,
      "end_t": 6.3,
      "n_frames": 190,
      "dur_s": 6.33
    },
    {
      "subtask_id": 1,
      "label": "lift the test tube and move it over the mortar",
      "start_frame": 190,
      "end_frame": 274,
      "start_t": 6.33,
      "end_t": 9.13,
      "n_frames": 85,
      "dur_s": 2.83
    },
    {
      "subtask_id": 2,
      "label": "pour the black powder into the mortar",
      "start_frame": 275,
      "end_frame": 411,
      "start_t": 9.17,
      "end_t": 13.7,
      "n_frames": 137,
      "dur_s": 4.57
    },
    {
      "subtask_id": 3,
      "label": "set down the test tube and pick up the pestle",
      "start_frame": 412,
      "end_frame": 733,
      "start_t": 13.73,
      "end_t": 24.43,
      "n_frames": 322,
      "dur_s": 10.73
    },
    {
      "subtask_id": 4,
      "label": "grind the powder in the mortar",
      "start_frame": 734,
      "end_frame": 1017,
      "start_t": 24.47,
      "end_t": 33.9,
      "n_frames": 284,
      "dur_s": 9.47
    },
    {
      "subtask_id": 5,
      "label": "lift the pestle and return to rest",
      "start_frame": 1018,
      "end_frame": 1156,
      "start_t": 33.93,
      "end_t": 38.53,
      "n_frames": 139,
      "dur_s": 4.63
    }
  ]
}