{
  "episode_index": 54,
  "task": "Pour the black powder into the mortar and grind.",
  "n_frames": 1154,
  "fps": 30,
  "annotator": "auto-signal",
  "method": "signal-derived (state-dim3 tube-held window + carrier-drift pour/grind)",
  "critical_points": [
    201,
    259,
    371,
    723,
    1027
  ],
  "subtask_starts": [
    0,
    201,
    259,
    371,
    723,
    1027
  ],
  "flags": [],
  "n_subtasks": 6,
  "subtasks": [
    {
      "subtask_id": 0,
      "label": "reach for the test tube",
      "start_frame": 0,
      "end_frame": 200,
      "start_t": 0.0,
      "end_t": 6.67,
      "n_frames": 201,
      "dur_s": 6.7
    },
    {
      "subtask_id": 1,
      "label": "lift the test tube and move it over the mortar",
      "start_frame": 201,
      "end_frame": 258,
      "start_t": 6.7,
      "end_t": 8.6,
      "n_frames": 58,
      "dur_s": 1.93
    },
    {
      "subtask_id": 2,
      "label": "pour the black powder into the mortar",
      "start_frame": 259,
      "end_frame": 370,
      "start_t": 8.63,
      "end_t": 12.33,
      "n_frames": 112,
      "dur_s": 3.73
    },
    {
      "subtask_id": 3,
      "label": "set down the test tube and pick up the pestle",
      "start_frame": 371,
      "end_frame": 722,
      "start_t": 12.37,
      "end_t": 24.07,
      "n_frames": 352,
      "dur_s": 11.73
    },
    {
      "subtask_id": 4,
      "label": "grind the powder in the mortar",
      "start_frame": 723,
      "end_frame": 1026,
      "start_t": 24.1,
      "end_t": 34.2,
      "n_frames": 304,
      "dur_s": 10.13
    },
    {
      "subtask_id": 5,
      "label": "lift the pestle and return to rest",
      "start_frame": 1027,
      "end_frame": 1153,
      "start_t": 34.23,
      "end_t": 38.43,
      "n_frames": 127,
      "dur_s": 4.23
    }
  ]
}